b_roller/__init__.py
b_roller/__main__.py
b_roller/credits.py
b_roller/fonts/Oswald-Bold.ttf
b_roller/fonts/Oswald-ExtraLight.ttf
b_roller/fonts/Oswald-Light.ttf
b_roller/fonts/Oswald-Medium.ttf
b_roller/fonts/Oswald-Regular.ttf
b_roller/fonts/Oswald-SemiBold.ttf
b_roller/fonts/__init__.py
b_roller/iconfinder.py
b_roller/pexels.py
b_roller/settings.py
b_roller/youtube.py
pytube/__init__.py
pytube/__main__.py
pytube/captions.py
pytube/cipher.py
pytube/cli.py
pytube/contrib/__init__.py
pytube/contrib/channel.py
pytube/contrib/playlist.py
pytube/contrib/search.py
pytube/exceptions.py
pytube/extract.py
pytube/helpers.py
pytube/innertube.py
pytube/itags.py
pytube/metadata.py
pytube/monostate.py
pytube/parser.py
pytube/query.py
pytube/request.py
pytube/streams.py
pytube/version.py
b_roller-1.6.2.dist-info/METADATA
b_roller-1.6.2.dist-info/WHEEL
b_roller-1.6.2.dist-info/entry_points.txt
b_roller-1.6.2.dist-info/RECORD
