Metadata-Version: 2.1
Name: b-roller
Version: 1.6.2
Summary: Download resources from several sources across the web
License: MIT
Author: Antonio Feregrino
Author-email: antonio.feregrino@gmail.com
Requires-Python: >=3.8,<4.0
Classifier: License :: OSI Approved :: MIT License
Classifier: Programming Language :: Python :: 3
Classifier: Programming Language :: Python :: 3.8
Classifier: Programming Language :: Python :: 3.9
Classifier: Programming Language :: Python :: 3.10
Classifier: Programming Language :: Python :: 3.11
Requires-Dist: ffmpeg-python (>=0.2.0,<0.3.0)
Requires-Dist: pillow (>=10.1.0,<11.0.0)
Requires-Dist: python-slugify
Requires-Dist: requests
Requires-Dist: rich (>=13.5.2,<14.0.0)
Requires-Dist: typer
Requires-Dist: urllib3 (<=2)
